datachecks/__init__.py
datachecks/__main__.py
datachecks/__version__.py
datachecks/cli/__init__.py
datachecks/cli/cli.py
datachecks/core/__init__.py
datachecks/core/common/__init__.py
datachecks/core/common/errors.py
datachecks/core/common/models/__init__.py
datachecks/core/common/models/configuration.py
datachecks/core/common/models/dashboard.py
datachecks/core/common/models/data_source_resource.py
datachecks/core/common/models/metric.py
datachecks/core/common/models/profile.py
datachecks/core/common/models/validation.py
datachecks/core/common/models/widget.py
datachecks/core/configuration/__init__.py
datachecks/core/configuration/config_loader.py
datachecks/core/configuration/configuration_parser.py
datachecks/core/configuration/configuration_parser_v1.py
datachecks/core/datasource/__init__.py
datachecks/core/datasource/base.py
datachecks/core/datasource/manager.py
datachecks/core/datasource/search_datasource.py
datachecks/core/datasource/sql_datasource.py
datachecks/core/inspect.py
datachecks/core/logger/__init__.py
datachecks/core/logger/base.py
datachecks/core/logger/default_logger.py
datachecks/core/metric/__init__.py
datachecks/core/metric/base.py
datachecks/core/metric/combined_metric.py
datachecks/core/metric/custom_metric.py
datachecks/core/metric/manager.py
datachecks/core/metric/numeric_metric.py
datachecks/core/metric/reliability_metric.py
datachecks/core/profiling/__init__.py
datachecks/core/profiling/datasource_profiling.py
datachecks/core/profiling/numeric_field_profiling.py
datachecks/core/profiling/text_field_profiling.py
datachecks/core/repository/__init__.py
datachecks/core/repository/metric_repository.py
datachecks/core/utils/__init__.py
datachecks/core/utils/log.py
datachecks/core/utils/tracking.py
datachecks/core/utils/utils.py
datachecks/core/validation/__init__.py
datachecks/core/validation/base.py
datachecks/core/validation/completeness_validation.py
datachecks/core/validation/custom_query_validation.py
datachecks-0.3.1.dist-info/LICENSE
datachecks-0.3.1.dist-info/METADATA
datachecks-0.3.1.dist-info/WHEEL
datachecks-0.3.1.dist-info/entry_points.txt
datachecks-0.3.1.dist-info/RECORD
