Metadata-Version: 2.1
Name: datachecks
Version: 0.3.1
Summary: Open Source Data Quality Monitoring
Home-page: https://github.com/waterdipai/datachecks
License: Apache-2.0
Author: Waterdip Labs
Author-email: hello@waterdip.ai
Requires-Python: >=3.9,<3.13
Classifier: Development Status :: 3 - Alpha
Classifier: Environment :: Console
Classifier: Intended Audience :: Developers
Classifier: Intended Audience :: Information Technology
Classifier: Intended Audience :: System Administrators
Classifier: License :: OSI Approved :: Apache Software License
Classifier: Programming Language :: Python :: 3
Classifier: Programming Language :: Python :: 3.9
Classifier: Programming Language :: Python :: 3.10
Classifier: Programming Language :: Python :: 3.11
Classifier: Programming Language :: Python :: 3.10
Classifier: Programming Language :: Python :: 3.11
Classifier: Programming Language :: Python :: 3.9
Classifier: Topic :: Database :: Database Engines/Servers
Classifier: Typing :: Typed
Provides-Extra: all
Provides-Extra: bigquery
Provides-Extra: databricks
Provides-Extra: elasticsearch
Provides-Extra: ms-sql
Provides-Extra: mysql
Provides-Extra: opensearch
Provides-Extra: postgres
Provides-Extra: snowflake
Requires-Dist: click (>=8.1.5,<9.0.0)
Requires-Dist: databricks-sql-connector (>=3.3.0,<4.0.0) ; extra == "databricks" or extra == "all"
Requires-Dist: elasticsearch (>=7.17.3,<8.0.0) ; extra == "elasticsearch" or extra == "all"
Requires-Dist: loguru (>=0.7.0,<0.8.0)
Requires-Dist: numpy (==1.26.4)
Requires-Dist: opensearch-py (>=2.2.0,<3.0.0) ; extra == "opensearch" or extra == "all"
Requires-Dist: psycopg2-binary (>=2.9.9,<3.0.0) ; extra == "postgres" or extra == "all"
Requires-Dist: pymysql[rsa] (>=1.1.0,<2.0.0) ; extra == "mysql" or extra == "all"
Requires-Dist: pyodbc (>=5.0.1,<6.0.0) ; extra == "ms-sql" or extra == "all"
Requires-Dist: pyparsing (>=3.1.1,<4.0.0)
Requires-Dist: python-dateutil (>=2.8.2,<3.0.0)
Requires-Dist: pytz (>=2023.3.post1,<2024.0)
Requires-Dist: pyyaml (>=6.0,<7.0)
Requires-Dist: requests (>=2.31.0,<3.0.0)
Requires-Dist: rich (>=13.5.2,<14.0.0)
Requires-Dist: snowflake-sqlalchemy (>=1.5.3,<2.0.0) ; extra == "snowflake" or extra == "all"
Requires-Dist: sqlalchemy (>=2.0.14,<2.1.0)
Requires-Dist: sqlalchemy-bigquery (>=1.8.0,<2.0.0) ; extra == "bigquery" or extra == "all"
Project-URL: Repository, https://github.com/waterdipai/datachecks
